preimutils/__init__.py
preimutils/classification/__init__.py
preimutils/classification/augment.py
preimutils/classification/run.py
preimutils/keypoint_detection/__init__.py
preimutils/keypoint_detection/cvat/__init__.py
preimutils/keypoint_detection/cvat/augment.py
preimutils/keypoint_detection/cvat/dataset.py
preimutils/keypoint_detection/cvat/img_aug.py
preimutils/keypoint_detection/cvat/load_data.py
preimutils/keypoint_detection/cvat/utils/__init__.py
preimutils/keypoint_detection/cvat/utils/utils.py
preimutils/object_detection/__init__.py
preimutils/object_detection/voc/__init__.py
preimutils/object_detection/voc/annotations_xml.py
preimutils/object_detection/voc/check_valid_label.py
preimutils/object_detection/voc/crop_from_point.py
preimutils/object_detection/voc/img_aug.py
preimutils/object_detection/voc/label_json.py
preimutils/object_detection/voc/rename_xml_path.py
preimutils/object_detection/voc/run.py
preimutils/object_detection/voc/separate_with_label.py
preimutils/object_detection/voc/shuffle_file.py
preimutils/object_detection/voc/train_validation_sep.py
preimutils/object_detection/voc/xml_to_csv.py
preimutils/object_detection/yolo/__init__.py
preimutils/object_detection/yolo/coco2yolo.py
preimutils/object_detection/yolo/img_aug.py
preimutils/object_detection/yolo/reader_writer.py
preimutils/object_detection/yolo/train_validation_sep.py
preimutils/object_detection/yolo/validating_data.py
preimutils/object_detection/yolo/utils/__init__.py
preimutils/object_detection/yolo/utils/utils.py
preimutils/segmentations/__init__.py
preimutils/segmentations/coco/__init__.py
preimutils/segmentations/coco/coco_manager.py
preimutils/segmentations/voc/__init__.py
preimutils/segmentations/voc/augment.py
preimutils/segmentations/voc/dataset.py
preimutils/segmentations/voc/utils/__init__.py
preimutils/segmentations/voc/utils/utils.py
preimutils-1.1.5.dist-info/LICENSE
preimutils-1.1.5.dist-info/METADATA
preimutils-1.1.5.dist-info/WHEEL
preimutils-1.1.5.dist-info/entry_points.txt
preimutils-1.1.5.dist-info/top_level.txt
preimutils-1.1.5.dist-info/RECORD
