Metadata-Version: 2.1
Name: preimutils
Version: 1.1.5
Summary: All you need to prepare and preprocess your annotated images
Home-page: https://github.com/mrl-amrl/preimutils
Download-URL: https://github.com/mrl-amrl/preimutils/archive/1.1.5.tar.gz
Author: Amir Sharifi
Author-email: ami_rsh@outlook.com
License: MIT
Keywords: computer vision,image processing,opencv,matplotlib,preprocess image,image dataset,pascal voc
License-File: LICENSE
Requires-Dist: pascal-voc-writer
Requires-Dist: tqdm
Requires-Dist: albumentations
Requires-Dist: pandas
Requires-Dist: imutils
Requires-Dist: opencv-python
Requires-Dist: imageio
Requires-Dist: pycocotools
Requires-Dist: shutils
Requires-Dist: xmltodict
Requires-Dist: numpy
Requires-Dist: matplotlib
